django_access_control/__init__.py
django_access_control/admin.py
django_access_control/auth_backend.py
django_access_control/models.py
django_access_control/permissions.py
django_access_control/querysets.py
django_access_control/utils.py
django_access_control-1.0.dist-info/LICENSE
django_access_control-1.0.dist-info/METADATA
django_access_control-1.0.dist-info/WHEEL
django_access_control-1.0.dist-info/top_level.txt
django_access_control-1.0.dist-info/RECORD
