Metadata-Version: 2.1
Name: django-access-control
Version: 1.0
Summary: Field and object level access control for Django
Home-page: https://github.com/django-access-control/django-access-control
Author: Eerik Sven Puudist
License: UNKNOWN
Project-URL: Bug Tracker, https://github.com/django-access-control/django-access-control/issues
Platform: UNKNOWN
Classifier: Programming Language :: Python :: 3
Classifier: License :: OSI Approved :: MIT License
Classifier: Operating System :: OS Independent
Requires-Python: >=3.6
License-File: LICENSE
Requires-Dist: django
